fortidlp/__init__.py
fortidlp/auth.py
fortidlp/connector.py
fortidlp/fortidlp.py
fortidlp-0.96.dist-info/licenses/LICENSE
fortidlp-0.96.dist-info/METADATA
fortidlp-0.96.dist-info/WHEEL
fortidlp-0.96.dist-info/top_level.txt
fortidlp-0.96.dist-info/RECORD
